Metadata-Version: 1.1
Name: snownlp
Version: 0.9.8.2
Summary: Python library for processing Chinese text
Home-page: https://github.com/isnowfy/snownlp
Author: isnowfy
Author-email: UNKNOWN
License: UNKNOWN
Platform: UNKNOWN
Classifier: Development Status :: 3 - Alpha
Classifier: Intended Audience :: Developers
Classifier: License :: OSI Approved :: MIT License
Classifier: Programming Language :: Python
